crsq_heap/__init__.py
crsq_heap/heap.py
crsq_heap-0.2.0.dist-info/METADATA
crsq_heap-0.2.0.dist-info/WHEEL
crsq_heap-0.2.0.dist-info/licenses/LICENSE
crsq_heap-0.2.0.dist-info/RECORD
